jsave/__init__.py
jsave/cmd/json/read.py
jsave/cmd/json/save.py
jsave/cmd/json/update.py
jsave/cmd/pickle/read.py
jsave/cmd/pickle/save.py
jsave/error.py
jsave/jsave.py
jsave/pickle.py
jsave/utils.py
jsave-1.6.4.dist-info/LICENSE
jsave-1.6.4.dist-info/METADATA
jsave-1.6.4.dist-info/WHEEL
jsave-1.6.4.dist-info/RECORD
