Metadata-Version: 2.3
Name: jsave
Version: 1.6.4
Summary: A simple python module for operating on mainly JSON files. While supporting other formats such as python pickling.
License: MIT
Author: Ethan Illingsworth
Requires-Python: >=3.9,<4.0
Classifier: License :: OSI Approved :: MIT License
Classifier: Programming Language :: Python :: 3
Classifier: Programming Language :: Python :: 3.9
Classifier: Programming Language :: Python :: 3.10
Classifier: Programming Language :: Python :: 3.11
Classifier: Programming Language :: Python :: 3.12
Classifier: Programming Language :: Python :: 3.13
Requires-Dist: colorxs (==1.0.1)
Requires-Dist: cryptography (>=43.0.3,<44.0.0)
Requires-Dist: listtypes (==1.0.1)
